{
  "gitSyncId": "691ed1a7d812511fbea0c055_c43ea20d-cc37-4f68-be2d-3a57d19ee98e",
  "id": "Page1_Insert_entities1",
  "pluginId": "mysql-plugin",
  "pluginType": "DB",
  "unpublishedAction": {
    "actionConfiguration": {
      "body": "INSERT INTO entities (namespace_id,name) VALUES ('{{(Table1.newRow || {}).namespace_id}}','{{(Table1.newRow || {}).name}}')",
      "encodeParamsToggle": true,
      "paginationType": "NONE",
      "pluginSpecifiedTemplates": [
        {
          "value": false
        }
      ],
      "timeoutInMillisecond": 10000
    },
    "confirmBeforeExecute": false,
    "datasource": {
      "id": "Untitled datasource 1",
      "isAutoGenerated": false,
      "name": "Untitled datasource 1",
      "pluginId": "mysql-plugin"
    },
    "dynamicBindingPathList": [
      {
        "key": "body"
      }
    ],
    "name": "Insert_entities1",
    "pageId": "Page1",
    "runBehaviour": "MANUAL",
    "userSetOnLoad": false
  }
}